awsecsconnect/__init__.py
awsecsconnect/awsecsconnect.py
awsecsconnect-0.0.6.dist-info/METADATA
awsecsconnect-0.0.6.dist-info/WHEEL
awsecsconnect-0.0.6.dist-info/entry_points.txt
awsecsconnect-0.0.6.dist-info/licenses/LICENSE
awsecsconnect-0.0.6.dist-info/RECORD
