Metadata-Version: 2.3
Name: awsecsconnect
Version: 0.0.6
Summary: Utility for more easily starting a shell on an AWS ECS Container
Author-email: Bob Jewell <bob@disclosed.org>
Classifier: License :: OSI Approved :: MIT License
Classifier: Operating System :: OS Independent
Classifier: Programming Language :: Python :: 3
Requires-Python: >=3.11
Requires-Dist: boto3
Requires-Dist: inquirer==3.3.0
